tsigua/__init__.py
tsigua/foo.py
tsigua-0.1.0.dist-info/METADATA
tsigua-0.1.0.dist-info/WHEEL
tsigua-0.1.0.dist-info/licenses/LICENSE
tsigua-0.1.0.dist-info/RECORD
