Metadata-Version: 2.4
Name: tsigua
Version: 0.1.0
Summary: Test uv for management.
Project-URL: Homepage, https://remexemer.github.io/tsigua/
Project-URL: Repository, https://github.com/remexemer/tsigua
Project-URL: Documentation, https://remexemer.github.io/tsigua/
Author-email: Ting-Shuo Hsu <tingshuo.hsu@gmail.com>
License-File: LICENSE
Keywords: python
Classifier: Intended Audience :: Developers
Classifier: Programming Language :: Python
Classifier: Programming Language :: Python :: 3
Classifier: Programming Language :: Python :: 3.9
Classifier: Programming Language :: Python :: 3.10
Classifier: Programming Language :: Python :: 3.11
Classifier: Programming Language :: Python :: 3.12
Classifier: Programming Language :: Python :: 3.13
Classifier: Topic :: Software Development :: Libraries :: Python Modules
Requires-Python: <4.0,>=3.9
